{
  "姓名": "杂货商埃德加",
  "年龄": "中年",
  "性别": "男",
  "职业": "黑心商人",
  "种族": "人类",
  "外观": "",
  "性格": "根据背景与行为可概括为：有明确立场、具备个人执念。",
  "背景描述": "游戏中那个和蔼的大叔，在同人文中揭露了资本家的真面目。他试图从这场灵魂危机中牟利，甚至想把“主角的圣殿骑士铠甲”骗过来当废铁卖。",
  "人物能力": "见设定全文中的能力与技能章节。",
  "特殊能力": "见设定全文中的特质/技能描述。",
  "属性面板": "",
  "哲学阵营": "中立（功利）",
  "名台词": "",
  "对待队伍": "与主角团保持功能性互动：提供情报/交易支援，以实用或利益为导向。",
  "在故事中的作用": "后勤交易与物资流通节点，主要为利益驱动。",
  "武装设定": "无专门战斗武装，以功能性交互为主。",
  "关联角色": [],
  "来源文件": "参考文件/妹神官同人/系统设定/故事背景设定-人物设定.md",
  "设定全文": "### **1. 城镇里的商人**\n**姓名：杂货商埃德加 (Edgar)**\n*   **职业：** 黑心商人\n*   **信条：** “金币万岁”\n*   **描述：**\n    游戏中那个和蔼的大叔，在同人文中揭露了资本家的真面目。他试图从这场灵魂危机中牟利，甚至想把“主角的圣殿骑士铠甲”骗过来当废铁卖。\n*   **名台词：**\n    *“灵魂？当然收。只要纯度够高，我这里甚至有去年的打折款。”*"
}